sample_size_calculator/__init__.py
sample_size_calculator/calculator.py
sample_size_calculator-1.0.0.dist-info/METADATA
sample_size_calculator-1.0.0.dist-info/WHEEL
sample_size_calculator-1.0.0.dist-info/RECORD
