Metadata-Version: 2.3
Name: sample-size-calculator
Version: 1.0.0
Summary: A comprehensive Python package for calculating sample sizes for various statistical tests including A/B tests, margin analysis, and log-normal distributions
Author: Tayo Ososanya
Author-email: ososanyatayo@gmail.com
Requires-Python: >=3.9,<3.12
Classifier: Programming Language :: Python :: 3
Classifier: Programming Language :: Python :: 3.9
Classifier: Programming Language :: Python :: 3.10
Classifier: Programming Language :: Python :: 3.11
Requires-Dist: matplotlib (>=3.7.0,<4.0.0)
Requires-Dist: numpy (>=1.24.0,<2.0.0)
Requires-Dist: scipy (>=1.10.0,<2.0.0)
Requires-Dist: statsmodels (>=0.14.0,<0.15.0)
Project-URL: Homepage, https://github.com/Tayoso/sample_size_calculator
Project-URL: Repository, https://github.com/Tayoso/sample_size_calculator
